pyipx800v3/__init__.py
pyipx800v3/pyipx800v3.py
pyipx800v3-0.1.0.dist-info/LICENSE
pyipx800v3-0.1.0.dist-info/METADATA
pyipx800v3-0.1.0.dist-info/WHEEL
pyipx800v3-0.1.0.dist-info/top_level.txt
pyipx800v3-0.1.0.dist-info/RECORD
